silverlabnwb/__init__.py
silverlabnwb/generate_extended_schema.py
silverlabnwb/header.py
silverlabnwb/imaging.py
silverlabnwb/metadata.py
silverlabnwb/metadata.yaml
silverlabnwb/metadata_gui.py
silverlabnwb/nwb_file.py
silverlabnwb/script.py
silverlabnwb/signature.py
silverlabnwb/silverlab.metadata.yaml
silverlabnwb/silverlab.namespace.yaml
silverlabnwb/silverlab.ophys.yaml
silverlabnwb/silverlab.roi.yaml
silverlabnwb/subsample_nwb.py
silverlabnwb/timings.py
silverlabnwb-0.2.0.dist-info/AUTHORS.rst
silverlabnwb-0.2.0.dist-info/LICENSE
silverlabnwb-0.2.0.dist-info/METADATA
silverlabnwb-0.2.0.dist-info/WHEEL
silverlabnwb-0.2.0.dist-info/entry_points.txt
silverlabnwb-0.2.0.dist-info/top_level.txt
silverlabnwb-0.2.0.dist-info/RECORD
