Metadata-Version: 2.1
Name: silverlabnwb
Version: 0.2.0
Summary: Python tools for working with Silver Lab data in the NWB2 format
Home-page: https://github.com/SilverLabUCL/PySilverLabNWB
Author: UCL Research Software Development Group
Author-email: rc-softdev@ucl.ac.uk
License: MIT license
Platform: UNKNOWN
Classifier: Development Status :: 3 - Alpha
Classifier: Intended Audience :: Developers
Classifier: Intended Audience :: Science/Research
Classifier: License :: OSI Approved :: MIT License
Classifier: Operating System :: Unix
Classifier: Operating System :: POSIX
Classifier: Operating System :: Microsoft :: Windows
Classifier: Programming Language :: Python
Classifier: Programming Language :: Python :: 3
Classifier: Programming Language :: Python :: 3.6
Classifier: Programming Language :: Python :: 3.7
Classifier: Programming Language :: Python :: Implementation :: CPython
Requires-Dist: pynwb (==1.3.2)
Requires-Dist: appdirs
Requires-Dist: h5py (>=2.7.1)
Requires-Dist: hdmf (<2.0.0)
Requires-Dist: nptdms (<=0.26.0)
Requires-Dist: numpy
Requires-Dist: pandas (>=0.20)
Requires-Dist: ruamel.yaml
Requires-Dist: tifffile[all]
Provides-Extra: test
Requires-Dist: pytest ; extra == 'test'
Requires-Dist: tox ; extra == 'test'
Provides-Extra: video
Requires-Dist: av ; extra == 'video'
